pqgit/Git-Icon-White.png
pqgit/__init__.py
pqgit/model.py
pqgit/pqgit.py
pqgit/ui.py
pqgit/util.py
pqgit-0.1.0.dist-info/LICENSE
pqgit-0.1.0.dist-info/METADATA
pqgit-0.1.0.dist-info/WHEEL
pqgit-0.1.0.dist-info/entry_points.txt
pqgit-0.1.0.dist-info/top_level.txt
pqgit-0.1.0.dist-info/RECORD
