Metadata-Version: 2.1
Name: pqgit
Version: 0.1.0
Summary: Python Qt Git browser
Home-page: https://github.com/raduvatav/pqgit
Author: Radu Vatav
Author-email: radu@vatav.cc
License: UNKNOWN
Platform: UNKNOWN
Classifier: Programming Language :: Python :: 3
Classifier: License :: OSI Approved :: GNU General Public License v3 (GPLv3)
Classifier: Operating System :: OS Independent
Requires-Python: >=3.8
Requires-Dist: pygit2
Requires-Dist: PySide2
